collagen/__init__.py
collagen/automation/__init__.py
collagen/automation/CD/__init__.py
collagen/automation/CI/__init__.py
collagen/core/__init__.py
collagen/data/__init__.py
collagen/datasets/__init__.py
collagen/device/__init__.py
collagen/ml/__init__.py
collagen/ml/aggregator/__init__.py
collagen/ml/aggregator/agg_operator.py
collagen/ml/evaluation/__init__.py
collagen/ml/helpers/__init__.py
collagen/ml/helpers/callbacks.py
collagen/ml/helpers/prompter.py
collagen/ml/loss_func/__init__.py
collagen/ml/model/__init__.py
collagen/ml/optimizer/__init__.py
collagen/simulation/__init__.py
collagen/simulation/flock/__init__.py
collagen/simulation/flock/client.py
collagen/simulation/flock/flock_sdk.py
collagen/utils/__init__.py
collagen/utils/arguments.py
collagen/utils/constants.py
collagen/utils/general.py
collagen/utils/helper.py
collagen/utils/model_utils.py
collagenai-0.0.1.dist-info/METADATA
collagenai-0.0.1.dist-info/WHEEL
collagenai-0.0.1.dist-info/top_level.txt
collagenai-0.0.1.dist-info/RECORD
