Metadata-Version: 2.1
Name: collagenai
Version: 0.0.1
Summary: CollaGen: Collaborative Learning Tool for Generative Model
Home-page: https://github.com/fedcontinuum/CollaGen
Author: Ray
Author-email: 170863868@qq.com
Keywords: Distributed Machine Learning,Federated Learning,Collaborative Learning,LLM,Generative Model,VLM
Classifier: Programming Language :: Python :: 3
Classifier: Programming Language :: Python :: 3.8
Classifier: Programming Language :: Python :: 3.9
Classifier: Programming Language :: Python :: 3.10
Classifier: License :: OSI Approved :: Apache Software License
Classifier: Operating System :: OS Independent
Requires-Python: >=3.11
Requires-Dist: loguru
Requires-Dist: tqdm
Requires-Dist: pyyaml
Requires-Dist: wandb
Requires-Dist: torch
Requires-Dist: torchvision
